{
  "generatedAt": "2026-04-08T10:18:21.091Z",
  "startedAt": "2026-04-08T10:18:19.353Z",
  "finishedAt": "2026-04-08T10:18:21.091Z",
  "projectPath": "./",
  "totalSteps": 32,
  "passedSteps": 32,
  "failedSteps": 0,
  "results": [
    {
      "label": "主入口语法检查",
      "commandText": "node -c game.js",
      "status": "passed",
      "startedAt": "2026-04-08T10:18:19.353Z",
      "finishedAt": "2026-04-08T10:18:19.444Z",
      "durationMs": 91,
      "errorMessage": ""
    },
    {
      "label": "启动编排语法检查",
      "commandText": "node -c architecture/boot/game-bootstrap.js",
      "status": "passed",
      "startedAt": "2026-04-08T10:18:19.449Z",
      "finishedAt": "2026-04-08T10:18:19.502Z",
      "durationMs": 53,
      "errorMessage": ""
    },
    {
      "label": "启动配置语法检查",
      "commandText": "node -c architecture/boot/config.js",
      "status": "passed",
      "startedAt": "2026-04-08T10:18:19.502Z",
      "finishedAt": "2026-04-08T10:18:19.552Z",
      "durationMs": 50,
      "errorMessage": ""
    },
    {
      "label": "启动安全语法检查",
      "commandText": "node -c architecture/boot/boot-safety.js",
      "status": "passed",
      "startedAt": "2026-04-08T10:18:19.552Z",
      "finishedAt": "2026-04-08T10:18:19.600Z",
      "durationMs": 48,
      "errorMessage": ""
    },
    {
      "label": "启动观测语法检查",
      "commandText": "node -c architecture/boot/boot-observer.js",
      "status": "passed",
      "startedAt": "2026-04-08T10:18:19.600Z",
      "finishedAt": "2026-04-08T10:18:19.654Z",
      "durationMs": 54,
      "errorMessage": ""
    },
    {
      "label": "启动恢复策略语法检查",
      "commandText": "node -c architecture/boot/recovery-strategy.js",
      "status": "passed",
      "startedAt": "2026-04-08T10:18:19.654Z",
      "finishedAt": "2026-04-08T10:18:19.703Z",
      "durationMs": 49,
      "errorMessage": ""
    },
    {
      "label": "运行时上下文语法检查",
      "commandText": "node -c architecture/boot/global-context.js",
      "status": "passed",
      "startedAt": "2026-04-08T10:18:19.703Z",
      "finishedAt": "2026-04-08T10:18:19.752Z",
      "durationMs": 49,
      "errorMessage": ""
    },
    {
      "label": "启动日志语法检查",
      "commandText": "node -c architecture/boot/boot-logger.js",
      "status": "passed",
      "startedAt": "2026-04-08T10:18:19.752Z",
      "finishedAt": "2026-04-08T10:18:19.800Z",
      "durationMs": 48,
      "errorMessage": ""
    },
    {
      "label": "平台策略语法检查",
      "commandText": "node -c architecture/boot/platform-strategy.js",
      "status": "passed",
      "startedAt": "2026-04-08T10:18:19.800Z",
      "finishedAt": "2026-04-08T10:18:19.849Z",
      "durationMs": 49,
      "errorMessage": ""
    },
    {
      "label": "性能策略语法检查",
      "commandText": "node -c architecture/boot/performance-strategy.js",
      "status": "passed",
      "startedAt": "2026-04-08T10:18:19.849Z",
      "finishedAt": "2026-04-08T10:18:19.897Z",
      "durationMs": 48,
      "errorMessage": ""
    },
    {
      "label": "系统信息语法检查",
      "commandText": "node -c architecture/boot/system-info.js",
      "status": "passed",
      "startedAt": "2026-04-08T10:18:19.897Z",
      "finishedAt": "2026-04-08T10:18:19.946Z",
      "durationMs": 49,
      "errorMessage": ""
    },
    {
      "label": "渲染策略语法检查",
      "commandText": "node -c architecture/boot/render-policies.js",
      "status": "passed",
      "startedAt": "2026-04-08T10:18:19.946Z",
      "finishedAt": "2026-04-08T10:18:19.994Z",
      "durationMs": 48,
      "errorMessage": ""
    },
    {
      "label": "运行桥接语法检查",
      "commandText": "node -c architecture/boot/runtime-bridge.js",
      "status": "passed",
      "startedAt": "2026-04-08T10:18:19.994Z",
      "finishedAt": "2026-04-08T10:18:20.044Z",
      "durationMs": 50,
      "errorMessage": ""
    },
    {
      "label": "应用生命周期语法检查",
      "commandText": "node -c architecture/boot/app-lifecycle.js",
      "status": "passed",
      "startedAt": "2026-04-08T10:18:20.044Z",
      "finishedAt": "2026-04-08T10:18:20.092Z",
      "durationMs": 48,
      "errorMessage": ""
    },
    {
      "label": "项目路径策略语法检查",
      "commandText": "node -c architecture/tools/project-paths.js",
      "status": "passed",
      "startedAt": "2026-04-08T10:18:20.093Z",
      "finishedAt": "2026-04-08T10:18:20.147Z",
      "durationMs": 54,
      "errorMessage": ""
    },
    {
      "label": "关键 JSON 格式化工具语法检查",
      "commandText": "node -c architecture/tools/format-project-json.js",
      "status": "passed",
      "startedAt": "2026-04-08T10:18:20.147Z",
      "finishedAt": "2026-04-08T10:18:20.197Z",
      "durationMs": 50,
      "errorMessage": ""
    },
    {
      "label": "Bundle 资产目录工具语法检查",
      "commandText": "node -c architecture/tools/generate-bundle-asset-catalog.js",
      "status": "passed",
      "startedAt": "2026-04-08T10:18:20.197Z",
      "finishedAt": "2026-04-08T10:18:20.247Z",
      "durationMs": 50,
      "errorMessage": ""
    },
    {
      "label": "素材可读性审计工具语法检查",
      "commandText": "node -c architecture/tools/generate-asset-readability-audit.js",
      "status": "passed",
      "startedAt": "2026-04-08T10:18:20.247Z",
      "finishedAt": "2026-04-08T10:18:20.301Z",
      "durationMs": 54,
      "errorMessage": ""
    },
    {
      "label": "音频使用审计工具语法检查",
      "commandText": "node -c architecture/tools/generate-audio-usage-audit.js",
      "status": "passed",
      "startedAt": "2026-04-08T10:18:20.301Z",
      "finishedAt": "2026-04-08T10:18:20.349Z",
      "durationMs": 48,
      "errorMessage": ""
    },
    {
      "label": "DuckBundle 木板语义化工具语法检查",
      "commandText": "node -c architecture/tools/semanticize-duckbundle-wood-assets.js",
      "status": "passed",
      "startedAt": "2026-04-08T10:18:20.349Z",
      "finishedAt": "2026-04-08T10:18:20.396Z",
      "durationMs": 47,
      "errorMessage": ""
    },
    {
      "label": "DuckBundle 背景语义化工具语法检查",
      "commandText": "node -c architecture/tools/semanticize-duckbundle-background-assets.js",
      "status": "passed",
      "startedAt": "2026-04-08T10:18:20.396Z",
      "finishedAt": "2026-04-08T10:18:20.443Z",
      "durationMs": 47,
      "errorMessage": ""
    },
    {
      "label": "DuckBundle 季节背景语义化工具语法检查",
      "commandText": "node -c architecture/tools/semanticize-duckbundle-seasonal-background-assets.js",
      "status": "passed",
      "startedAt": "2026-04-08T10:18:20.443Z",
      "finishedAt": "2026-04-08T10:18:20.491Z",
      "durationMs": 48,
      "errorMessage": ""
    },
    {
      "label": "HomeBundle 素材语义化工具语法检查",
      "commandText": "node -c architecture/tools/semanticize-homebundle-assets.js",
      "status": "passed",
      "startedAt": "2026-04-08T10:18:20.491Z",
      "finishedAt": "2026-04-08T10:18:20.540Z",
      "durationMs": 49,
      "errorMessage": ""
    },
    {
      "label": "uiBundle 图鉴皮肤页语义化工具语法检查",
      "commandText": "node -c architecture/tools/semanticize-uibundle-book-skin-assets.js",
      "status": "passed",
      "startedAt": "2026-04-08T10:18:20.540Z",
      "finishedAt": "2026-04-08T10:18:20.606Z",
      "durationMs": 66,
      "errorMessage": ""
    },
    {
      "label": "uiBundle 设置模块语义化工具语法检查",
      "commandText": "node -c architecture/tools/semanticize-uibundle-settings-assets.js",
      "status": "passed",
      "startedAt": "2026-04-08T10:18:20.606Z",
      "finishedAt": "2026-04-08T10:18:20.656Z",
      "durationMs": 50,
      "errorMessage": ""
    },
    {
      "label": "旧路径兼容校验工具语法检查",
      "commandText": "node -c architecture/tools/check-legacy-runtime-compat.js",
      "status": "passed",
      "startedAt": "2026-04-08T10:18:20.656Z",
      "finishedAt": "2026-04-08T10:18:20.706Z",
      "durationMs": 50,
      "errorMessage": ""
    },
    {
      "label": "迭代报告生成器语法检查",
      "commandText": "node -c architecture/tools/generate-iteration-report.js",
      "status": "passed",
      "startedAt": "2026-04-08T10:18:20.706Z",
      "finishedAt": "2026-04-08T10:18:20.756Z",
      "durationMs": 50,
      "errorMessage": ""
    },
    {
      "label": "迭代流水线语法检查",
      "commandText": "node -c architecture/tools/run-iteration-cycle.js",
      "status": "passed",
      "startedAt": "2026-04-08T10:18:20.756Z",
      "finishedAt": "2026-04-08T10:18:20.804Z",
      "durationMs": 48,
      "errorMessage": ""
    },
    {
      "label": "架构风格检查",
      "commandText": "node architecture/tools/check-architecture-style.js",
      "status": "passed",
      "startedAt": "2026-04-08T10:18:20.804Z",
      "finishedAt": "2026-04-08T10:18:20.865Z",
      "durationMs": 61,
      "errorMessage": ""
    },
    {
      "label": "素材分层检查",
      "commandText": "node architecture/tools/check-asset-code-separation.js",
      "status": "passed",
      "startedAt": "2026-04-08T10:18:20.865Z",
      "finishedAt": "2026-04-08T10:18:20.960Z",
      "durationMs": 95,
      "errorMessage": ""
    },
    {
      "label": "旧路径运行时兼容检查",
      "commandText": "node architecture/tools/check-legacy-runtime-compat.js",
      "status": "passed",
      "startedAt": "2026-04-08T10:18:20.960Z",
      "finishedAt": "2026-04-08T10:18:21.026Z",
      "durationMs": 66,
      "errorMessage": ""
    },
    {
      "label": "运行安全校验",
      "commandText": "node architecture/tools/verify-runtime-safety.js",
      "status": "passed",
      "startedAt": "2026-04-08T10:18:21.026Z",
      "finishedAt": "2026-04-08T10:18:21.091Z",
      "durationMs": 65,
      "errorMessage": ""
    }
  ]
}
